abcdefgh/__init__.py
abcdefgh/membrane_test.py
abcdefgh-0.0.1.dist-info/LICENSE.txt
abcdefgh-0.0.1.dist-info/METADATA
abcdefgh-0.0.1.dist-info/WHEEL
abcdefgh-0.0.1.dist-info/top_level.txt
abcdefgh-0.0.1.dist-info/RECORD
