Metadata-Version: 2.1
Name: abcdefgh
Version: 0.0.1
Summary: A package for electrophysiology data analysis
Home-page: UNKNOWN
Author: Alexia Montalant
Author-email: alexia.montalant@orange.fr
License: UNKNOWN
Platform: UNKNOWN
Classifier: Programming Language :: Python :: 3
Classifier: License :: OSI Approved :: MIT License
Classifier: Operating System :: OS Independent
Requires-Python: >=3.6
